mongofire/__init__.py
mongofire/collection.py
mongofire/document.py
mongofire/errors.py
mongofire/field.py
mongofire/mongodb.py
mongofire/mongofire.py
mongofire/query.py
mongofire/results.py
mongofire-0.0.1.dist-info/LICENSE
mongofire-0.0.1.dist-info/METADATA
mongofire-0.0.1.dist-info/WHEEL
mongofire-0.0.1.dist-info/top_level.txt
mongofire-0.0.1.dist-info/RECORD
