Metadata-Version: 2.1
Name: mongofire
Version: 0.0.1
Summary: A simple MongoDB python driver
Author-email: PSH-TEAM <pshteam.developers@gmail.com>
Project-URL: Homepage, https://github.com/psh-developers/mongofire
Project-URL: Bug Tracker, https://github.com/psh-developers/mongofire/issues
Project-URL: Documentation, https://mongofire.readthedocs.io
Classifier: Programming Language :: Python :: 3
Classifier: License :: OSI Approved :: MIT License
Classifier: Operating System :: OS Independent
Requires-Python: >=3.7
License-File: LICENSE
